{
  "type":"ClutterGroup",
  "id":"actor"
  "x": 0,
  "y": 2,
  "width":651,
  "height":326,
  "depth":0.000,
  "opacity":255,
  "scale-x":1.000,
  "scale-y":1.000,
  "rotation-angle-z":0.000,
  "anchor-x":0.000,
  "anchor-y":0.000,
  "children":[
  {
    "type":"ClutterText",
    "x":93,
    "y":107,
    "width":567,
    "height":179,
    "depth":0.000,
    "opacity":255,
    "scale-x":1.000,
    "scale-y":1.000,
    "rotation-angle-z":0.000,
    "anchor-x":0.000,
    "anchor-y":0.000,
    "font-name":"Sans 10",
    "text":"tree drag and drop
keybindings
ui for hyperlinks,
css inspector/editor
color picker
navigation history?
proper json-glib based serialization (needed at least for color)
custom property editors for common classes",
    "use-markup":false,
    "line-wrap":true,
    "justify":false,
    "position":30,
    "selection-bound":-1,
    "cursor-visible":true,
    "cursor-size":2,
    "editable":false,
    "selectable":true,
    "activatable":false,
    "password-char":0,
    "max-length":0,
    "single-line-mode":false,
  }
  ,
  {
    "type":"ClutterText",
    "x":93,
    "y":65,
    "width":153,
    "height":40,
    "depth":0.000,
    "opacity":255,
    "scale-x":1.000,
    "scale-y":1.000,
    "rotation-angle-z":0.000,
    "anchor-x":0.000,
    "anchor-y":0.000,
    "font-name":"Sans 20",
    "text":"Todo List:",
    "use-markup":false,
    "line-wrap":false,
    "justify":false,
    "position":-1,
    "selection-bound":-1,
    "cursor-visible":true,
    "cursor-size":2,
    "editable":false,
    "selectable":true,
    "activatable":false,
    "password-char":0,
    "max-length":0,
    "single-line-mode":false,
  }
  ]
}
